notebooktoall/__init__.py
notebooktoall/transform.py
notebooktoall-0.2.3.dist-info/AUTHORS.rst
notebooktoall-0.2.3.dist-info/LICENSE
notebooktoall-0.2.3.dist-info/METADATA
notebooktoall-0.2.3.dist-info/WHEEL
notebooktoall-0.2.3.dist-info/top_level.txt
notebooktoall-0.2.3.dist-info/RECORD
