Metadata-Version: 2.1
Name: notebooktoall
Version: 0.2.3
Summary: The coolest way to transform Jupyter Notebooks.
Home-page: https://github.com/notebooktoall/notebooktoall
Author: Jeff Hale
Author-email: jeffmshale@gmail.com
License: GNU General Public License v3
Keywords: notebooktoall
Platform: UNKNOWN
Classifier: Development Status :: 4 - Beta
Classifier: Intended Audience :: Developers
Classifier: License :: OSI Approved :: GNU General Public License v3 (GPLv3)
Classifier: Natural Language :: English
Classifier: Programming Language :: Python :: 3
Classifier: Programming Language :: Python :: 3.6
Classifier: Programming Language :: Python :: 3.7
Requires-Dist: ipython (>=6)
Requires-Dist: nbformat (>=4)
Requires-Dist: nbconvert (>=5)
Requires-Dist: requests (>=2)
